lego_console/__init__.py
lego_console/cli.py
lego_console/lego_console.py
lego_console/menus.py
lego_console/utils.py
tests/__init__.py
lego_console-0.1.1.dist-info/LICENSE.md
lego_console-0.1.1.dist-info/METADATA
lego_console-0.1.1.dist-info/WHEEL
lego_console-0.1.1.dist-info/entry_points.txt
lego_console-0.1.1.dist-info/top_level.txt
lego_console-0.1.1.dist-info/RECORD
